Metadata-Version: 1.0
Name: gubi-distributions
Version: 0.1
Summary: Normal/Gaussian and Binomial distributions
Home-page: UNKNOWN
Author: Samson Adetutu
Author-email: UNKNOWN
License: UNKNOWN
Platform: UNKNOWN
